sphinx_list_items/__init__.py
sphinx_list_items/figures.py
sphinx_list_items/tables.py
sphinx_list_items/utils.py
sphinx_list_items/versions.py
sphinx_list_items-1.0.0.dist-info/licenses/LICENSE
sphinx_list_items-1.0.0.dist-info/METADATA
sphinx_list_items-1.0.0.dist-info/WHEEL
sphinx_list_items-1.0.0.dist-info/top_level.txt
sphinx_list_items-1.0.0.dist-info/RECORD
