Metadata-Version: 2.4
Name: sphinx-list-items
Version: 1.0.0
Summary: A Sphinx extension to list items such as figures, tables, versionadded, etc.
Author-email: JoKneeMo <jokneemo@example.com>
License-Expression: GPL-3.0-only
Project-URL: Homepage, https://sphinx-list-items.jokneemo.com
Project-URL: Documentation, https://sphinx-list-items.jokneemo.com
Project-URL: Repository, https://github.com/JoKneeMo/sphinx-list-items
Project-URL: Issues, https://github.com/JoKneeMo/sphinx-list-items/issues
Keywords: Sphinx,Extension,list,sphinx-list,list-items
Classifier: Development Status :: 5 - Production/Stable
Classifier: Intended Audience :: Developers
Classifier: Topic :: Documentation :: Sphinx
Classifier: Framework :: Sphinx :: Extension
Classifier: Programming Language :: Python
Classifier: Programming Language :: Python :: 3
Classifier: Programming Language :: Python :: 3.7
Classifier: Programming Language :: Python :: 3.8
Classifier: Programming Language :: Python :: 3.9
Classifier: Programming Language :: Python :: 3.10
Classifier: Programming Language :: Python :: 3.11
Classifier: Programming Language :: Python :: 3.12
Requires-Python: >=3.7
License-File: LICENSE
Requires-Dist: sphinx>=5.0.2
Dynamic: license-file
